uipath_connectors/box_box/__init__.py
uipath_connectors/box_box/client.py
uipath_connectors/box_box/errors.py
uipath_connectors/box_box/py.typed
uipath_connectors/box_box/types.py
uipath_connectors/box_box/api/__init__.py
uipath_connectors/box_box/api/add_shared_link_to_file/__init__.py
uipath_connectors/box_box/api/add_shared_link_to_file/add_shared_linktoa_file.py
uipath_connectors/box_box/api/add_shared_link_to_folder/__init__.py
uipath_connectors/box_box/api/add_shared_link_to_folder/add_shared_linktoa_folder.py
uipath_connectors/box_box/api/cancel_sign_request/__init__.py
uipath_connectors/box_box/api/cancel_sign_request/cancel_sign_request.py
uipath_connectors/box_box/api/copy_file/__init__.py
uipath_connectors/box_box/api/copy_file/copy_file.py
uipath_connectors/box_box/api/copy_folder/__init__.py
uipath_connectors/box_box/api/copy_folder/copy_folder.py
uipath_connectors/box_box/api/create_sign_request/__init__.py
uipath_connectors/box_box/api/create_sign_request/create_sign_request.py
uipath_connectors/box_box/api/files/__init__.py
uipath_connectors/box_box/api/files/delete_file.py
uipath_connectors/box_box/api/files/get_file_info.py
uipath_connectors/box_box/api/files_content/__init__.py
uipath_connectors/box_box/api/files_content/download_file.py
uipath_connectors/box_box/api/folder_items/__init__.py
uipath_connectors/box_box/api/folder_items/get_folder_items.py
uipath_connectors/box_box/api/folders/__init__.py
uipath_connectors/box_box/api/folders/create_folder.py
uipath_connectors/box_box/api/folders/delete_folder.py
uipath_connectors/box_box/api/search_for_content/__init__.py
uipath_connectors/box_box/api/search_for_content/search.py
uipath_connectors/box_box/api/sign_requests/__init__.py
uipath_connectors/box_box/api/sign_requests/list_sign_request.py
uipath_connectors/box_box/api/sign_requests_resend/__init__.py
uipath_connectors/box_box/api/sign_requests_resend/resend_sign_request.py
uipath_connectors/box_box/api/upload_file/__init__.py
uipath_connectors_box_box-1.10.27.dev12.dist-info/METADATA
uipath_connectors_box_box-1.10.27.dev12.dist-info/WHEEL
uipath_connectors_box_box-1.10.27.dev12.dist-info/entry_points.txt
uipath_connectors_box_box-1.10.27.dev12.dist-info/top_level.txt
uipath_connectors_box_box-1.10.27.dev12.dist-info/RECORD
